{
    "className": "org.joget.apps.form.model.Form",
    "elements": [{
        "className": "org.joget.apps.form.model.Section",
        "elements": [{
            "className": "org.joget.apps.form.model.Column",
            "elements": [
                {
                    "className": "org.joget.apps.form.lib.TextField",
                    "properties": {
                        "encryption": "",
                        "id": "nadiv",
                        "label": "Nama Divisi",
                        "maxlength": "",
                        "placeholder": "Masukan Nama Divisi",
                        "readonly": "",
                        "readonlyLabel": "",
                        "size": "",
                        "storeNumeric": "",
                        "style": "",
                        "validator": {
                            "className": "org.joget.apps.form.lib.DuplicateValueValidator",
                            "properties": {
                                "errorDuplicateMsg": "Nama Divisi telah ada sebelumnya",
                                "errorFormatMsg": "",
                                "fieldId": "nadiv",
                                "formDefId": "divisi",
                                "mandatory": "true",
                                "regex": ""
                            }
                        },
                        "value": "",
                        "workflowVariable": ""
                    }
                },
                {
                    "className": "org.joget.apps.form.lib.TextField",
                    "properties": {
                        "encryption": "",
                        "id": "asdiv",
                        "label": "SINGKATAN",
                        "maxlength": "",
                        "placeholder": "Ex. SISFO",
                        "readonly": "",
                        "readonlyLabel": "",
                        "size": "",
                        "storeNumeric": "",
                        "style": "",
                        "validator": {
                            "className": "org.joget.apps.form.lib.DuplicateValueValidator",
                            "properties": {
                                "errorDuplicateMsg": "Nama Alias Telah ada Sebelumnya",
                                "errorFormatMsg": "",
                                "fieldId": "asdiv",
                                "formDefId": "divisi",
                                "mandatory": "true",
                                "regex": ""
                            }
                        },
                        "value": "",
                        "workflowVariable": ""
                    }
                },
                {
                    "className": "org.joget.apps.form.lib.SelectBox",
                    "properties": {
                        "controlField": "",
                        "id": "lokdiv",
                        "label": "LOKASI",
                        "multiple": "",
                        "options": [],
                        "optionsBinder": {
                            "className": "org.joget.apps.form.lib.FormOptionsBinder",
                            "properties": {
                                "addEmptyOption": "true",
                                "cacheInterval": "",
                                "emptyLabel": "Pilih Lokasi",
                                "extraCondition": "",
                                "formDefId": "kantor",
                                "groupingColumn": "",
                                "idColumn": "",
                                "labelColumn": "nakan",
                                "useAjax": ""
                            }
                        },
                        "readonly": "",
                        "readonlyLabel": "",
                        "size": "",
                        "validator": {
                            "className": "org.joget.apps.form.lib.DuplicateValueValidator",
                            "properties": {
                                "errorDuplicateMsg": "",
                                "errorFormatMsg": "",
                                "fieldId": "nadiv",
                                "formDefId": "divisi",
                                "mandatory": "true",
                                "regex": ""
                            }
                        },
                        "value": "",
                        "workflowVariable": ""
                    }
                },
                {
                    "className": "org.joget.plugin.enterprise.CaptchaField",
                    "properties": {
                        "id": "capdiv",
                        "label": "KONFIRMASI - (Anda Bukanlah Robot)"
                    }
                },
                {
                    "className": "org.joget.apps.form.lib.HiddenField",
                    "properties": {
                        "id": "crediv",
                        "useDefaultWhenEmpty": "",
                        "value": "#currentUser.username#",
                        "workflowVariable": ""
                    }
                },
                {
                    "className": "org.joget.apps.form.lib.HiddenField",
                    "properties": {
                        "id": "datediv",
                        "useDefaultWhenEmpty": "",
                        "value": "#date.yyyy-MM-dd#",
                        "workflowVariable": ""
                    }
                }
            ],
            "properties": {"width": "100%"}
        }],
        "properties": {
            "id": "section1",
            "label": "Section"
        }
    }],
    "properties": {
        "description": "",
        "id": "divisi",
        "loadBinder": {
            "className": "org.joget.apps.form.lib.WorkflowFormBinder",
            "properties": {}
        },
        "name": "DIVISI",
        "noPermissionMessage": "",
        "permission": {
            "className": "",
            "properties": {}
        },
        "postProcessor": {
            "className": "",
            "properties": {}
        },
        "postProcessorRunOn": "create",
        "storeBinder": {
            "className": "org.joget.apps.form.lib.WorkflowFormBinder",
            "properties": {}
        },
        "tableName": "master_divisi"
    }
}